ditto/__init__.py
ditto/cli.py
ditto/enumerations.py
ditto/readers/__init__.py
ditto/readers/reader.py
ditto/readers/cim_iec_61968_13/__init__.py
ditto/readers/cim_iec_61968_13/cim_mapper.py
ditto/readers/cim_iec_61968_13/common.py
ditto/readers/cim_iec_61968_13/length_units.py
ditto/readers/cim_iec_61968_13/queries.py
ditto/readers/cim_iec_61968_13/reader.py
ditto/readers/cim_iec_61968_13/components/__init__.py
ditto/readers/cim_iec_61968_13/components/distribution_bus.py
ditto/readers/cim_iec_61968_13/components/distribution_capacitor.py
ditto/readers/cim_iec_61968_13/components/distribution_load.py
ditto/readers/cim_iec_61968_13/components/distribution_regulator.py
ditto/readers/cim_iec_61968_13/components/distribution_transformer.py
ditto/readers/cim_iec_61968_13/components/distribution_voltage_source.py
ditto/readers/cim_iec_61968_13/components/matrix_branch.py
ditto/readers/cim_iec_61968_13/components/matrix_impedance_switch.py
ditto/readers/cim_iec_61968_13/controllers/__init__.py
ditto/readers/cim_iec_61968_13/controllers/regulator_controller.py
ditto/readers/cim_iec_61968_13/equipment/__init__.py
ditto/readers/cim_iec_61968_13/equipment/capacitor_equipment.py
ditto/readers/cim_iec_61968_13/equipment/distribution_transformer_equipment.py
ditto/readers/cim_iec_61968_13/equipment/load_equipment.py
ditto/readers/cim_iec_61968_13/equipment/matrix_branch_equipment.py
ditto/readers/cim_iec_61968_13/equipment/voltage_source_equipment.py
ditto/readers/cim_iec_61968_13/equipment/winding_equipment.py
ditto/readers/opendss/__init__.py
ditto/readers/opendss/common.py
ditto/readers/opendss/graph_utils.py
ditto/readers/opendss/reader.py
ditto/readers/opendss/components/__init__.py
ditto/readers/opendss/components/branches.py
ditto/readers/opendss/components/buses.py
ditto/readers/opendss/components/cables.py
ditto/readers/opendss/components/capacitors.py
ditto/readers/opendss/components/conductors.py
ditto/readers/opendss/components/fuses.py
nrel_ditto-0.0.17.dist-info/METADATA
nrel_ditto-0.0.17.dist-info/WHEEL
nrel_ditto-0.0.17.dist-info/entry_points.txt
nrel_ditto-0.0.17.dist-info/RECORD
