Metadata-Version: 2.4
Name: NREL-ditto
Version: 0.0.17
Summary: Many to one to many distrbution system model converter 
Project-URL: Documentation, https://github.com/NREL-Distribution-Suites/ditto#readme
Project-URL: Issues, https://github.com/NREL-Distribution-Suites/ditto/issues
Project-URL: Source, https://github.com/NREL-Distribution-Suites/ditto
Author-email: Aadil Latif <aadil.latif@gmail.com>
License-Expression: MIT
Classifier: Development Status :: 4 - Beta
Classifier: Programming Language :: Python
Classifier: Programming Language :: Python :: 3.10
Classifier: Programming Language :: Python :: 3.11
Classifier: Programming Language :: Python :: 3.12
Classifier: Programming Language :: Python :: Implementation :: CPython
Classifier: Programming Language :: Python :: Implementation :: PyPy
Requires-Python: >=3.11
Requires-Dist: grid-data-models==2.2.1
Requires-Dist: nrel-altdss-schema==0.0.2
Requires-Dist: opendssdirect-py
Requires-Dist: rdflib
Requires-Dist: typer
Provides-Extra: dev
Requires-Dist: pytest; extra == 'dev'
Requires-Dist: ruff; extra == 'dev'
Requires-Dist: typer; extra == 'dev'
Provides-Extra: doc
Requires-Dist: autodoc-pydantic; extra == 'doc'
Requires-Dist: myst-parser; extra == 'doc'
Requires-Dist: pydata-sphinx-theme; extra == 'doc'
Requires-Dist: sphinx; extra == 'doc'
Requires-Dist: sphinxcontrib-mermaid; extra == 'doc'
